LICENSE
README.rst
setup.cfg
setup.py
django_mpesa_express.egg-info/PKG-INFO
django_mpesa_express.egg-info/SOURCES.txt
django_mpesa_express.egg-info/dependency_links.txt
django_mpesa_express.egg-info/top_level.txt
express/__init__.py
express/admin.py
express/apps.py
express/gateway.py
express/models.py
express/serializers.py
express/tests.py
express/urls.py
express/views.py
express/migrations/0001_initial.py
express/migrations/__init__.py