Metadata-Version: 2.1
Name: django-mpesa-express
Version: 0.1
Summary: a django app with mpesa express integration
Home-page: https://github.com/kangangi/MpesaExpressDjangoIntegration
Author: Wanjiku Kangangi
Author-email: wanjikukangangi@gmail.com
License: MIT
Classifier: Environment :: Web Environment
Classifier: Framework :: Django
Classifier: Framework :: Django :: 5.0
Classifier: Intended Audience :: Developers
Classifier: License :: OSI Approved :: MIT License
Classifier: Operating System :: OS Independent
Classifier: Programming Language :: Python
Classifier: Programming Language :: Python :: 3.10
License-File: LICENSE
